NorenRestApiPy/NorenApi.py
NorenRestApiPy/__init__.py
NorenRestApi-0.0.34.dist-info/LICENSE
NorenRestApi-0.0.34.dist-info/METADATA
NorenRestApi-0.0.34.dist-info/WHEEL
NorenRestApi-0.0.34.dist-info/top_level.txt
NorenRestApi-0.0.34.dist-info/RECORD
