Metadata-Version: 2.1
Name: NorenRestApi
Version: 0.0.34
Summary: A package for NorenOMS
Home-page: UNKNOWN
Author: KumarAnand
Author-email: kumar.anand@kambala.co.in
License: UNKNOWN
Platform: UNKNOWN
Classifier: Programming Language :: Python :: 3
Classifier: License :: Other/Proprietary License
Classifier: Operating System :: OS Independent
License-File: LICENSE
Requires-Dist: PyYAML
Requires-Dist: pandas
Requires-Dist: requests
Requires-Dist: websocket-client
